scrab/__init__.py
scrab/formatter.py
scrab/parser.py
scrab/io/__init__.py
scrab/io/web_client.py
scrab/web/__init__.py
scrab/web/web_client.py
scrab-0.0.6.data/scripts/scrab
scrab-0.0.6.dist-info/LICENSE
scrab-0.0.6.dist-info/METADATA
scrab-0.0.6.dist-info/WHEEL
scrab-0.0.6.dist-info/top_level.txt
scrab-0.0.6.dist-info/RECORD
