Metadata-Version: 2.1
Name: scrab
Version: 0.0.6
Summary: Fast and easy to use scraper for the content-centered web pages, e.g. blog posts, news, etc.
Home-page: https://github.com/gindex/scrab
Author: Yevgen Pikus
Author-email: yevgen.pikus@gmail.com
License: MIT
Keywords: scrab scraper crawler extractor converter web content html text
Platform: UNKNOWN
Classifier: Development Status :: 2 - Pre-Alpha
Classifier: Environment :: Console
Classifier: Intended Audience :: End Users/Desktop
Classifier: Intended Audience :: Science/Research
Classifier: Intended Audience :: Developers
Classifier: License :: OSI Approved :: MIT License
Classifier: Operating System :: OS Independent
Classifier: Programming Language :: Python :: 3.8
Classifier: Topic :: Utilities
Classifier: Topic :: Text Processing
Requires-Python: >=3.8
Requires-Dist: click
Requires-Dist: requests
Requires-Dist: lxml
